{"chart":{"result":[{"meta":{"currency":"USD","symbol":"ESHAR","exchangeName":"NGM","fullExchangeName":"NasdaqGM","instrumentType":"EQUITY","firstTradeDate":null,"regularMarketTime":1733518800,"hasPrePostMarketData":true,"gmtoffset":-18000,"timezone":"EST","exchangeTimezoneName":"America/New_York","regularMarketPrice":0.089,"fiftyTwoWeekHigh":0.135,"fiftyTwoWeekLow":0.083,"regularMarketDayHigh":0.135,"regularMarketDayLow":0.083,"regularMarketVolume":25796,"longName":"ESH Acquisition Corp.","shortName":"ESH Acquisition Corp.","chartPreviousClose":0.1,"priceHint":4,"currentTradingPeriod":{"pre":{"timezone":"EST","start":1733475600,"end":1733495400,"gmtoffset":-18000},"regular":{"timezone":"EST","start":1733495400,"end":1733518800,"gmtoffset":-18000},"post":{"timezone":"EST","start":1733518800,"end":1733533200,"gmtoffset":-18000}},"dataGranularity":"1d","range":"","validRanges":["1d","5d"]},"timestamp":[1733518800],"indicators":{"quote":[{"close":[0.08869999647140503],"high":[0.13500000536441803],"low":[0.08299999684095383],"open":[0.08299999684095383],"volume":[25796]}],"adjclose":[{"adjclose":[0.08869999647140503]}]}}],"error":null}}