{"chart":{"result":[{"meta":{"currency":"USD","symbol":"MNTSW","exchangeName":"NCM","fullExchangeName":"NasdaqCM","instrumentType":"EQUITY","firstTradeDate":null,"regularMarketTime":1733518800,"hasPrePostMarketData":true,"gmtoffset":-18000,"timezone":"EST","exchangeTimezoneName":"America/New_York","regularMarketPrice":0.014,"fiftyTwoWeekHigh":0.014,"fiftyTwoWeekLow":0.011,"regularMarketDayHigh":0.014,"regularMarketDayLow":0.011,"regularMarketVolume":166726,"longName":"Momentus Inc.","chartPreviousClose":0.013,"priceHint":4,"currentTradingPeriod":{"pre":{"timezone":"EST","start":1733475600,"end":1733495400,"gmtoffset":-18000},"regular":{"timezone":"EST","start":1733495400,"end":1733518800,"gmtoffset":-18000},"post":{"timezone":"EST","start":1733518800,"end":1733533200,"gmtoffset":-18000}},"dataGranularity":"1d","range":"","validRanges":["1d","5d"]},"timestamp":[1733518800],"indicators":{"quote":[{"volume":[166726],"low":[0.010700000450015068],"open":[0.010999999940395355],"high":[0.013500000350177288],"close":[0.013500000350177288]}],"adjclose":[{"adjclose":[0.013500000350177288]}]}}],"error":null}}