{"chart":{"result":[{"meta":{"currency":"USD","symbol":"PRLHW","exchangeName":"NCM","fullExchangeName":"NasdaqCM","instrumentType":"EQUITY","firstTradeDate":null,"regularMarketTime":1733518800,"hasPrePostMarketData":true,"gmtoffset":-18000,"timezone":"EST","exchangeTimezoneName":"America/New_York","regularMarketPrice":0.0213,"fiftyTwoWeekHigh":0.0349,"fiftyTwoWeekLow":0.0213,"regularMarketDayHigh":0.0349,"regularMarketDayLow":0.0213,"regularMarketVolume":600,"longName":"Pearl Holdings Acquisition Corp","shortName":"Pearl Holdings Acquisition Corp","chartPreviousClose":0.0293,"priceHint":4,"currentTradingPeriod":{"pre":{"timezone":"EST","start":1733475600,"end":1733495400,"gmtoffset":-18000},"regular":{"timezone":"EST","start":1733495400,"end":1733518800,"gmtoffset":-18000},"post":{"timezone":"EST","start":1733518800,"end":1733533200,"gmtoffset":-18000}},"dataGranularity":"1d","range":"","validRanges":["1d","5d"]},"timestamp":[1733518800],"indicators":{"quote":[{"volume":[600],"open":[0.0348999984562397],"low":[0.021299999207258224],"close":[0.021299999207258224],"high":[0.0348999984562397]}],"adjclose":[{"adjclose":[0.021299999207258224]}]}}],"error":null}}